{
  "Alamance, North Carolina": {
    "state": "37",
    "place": "00640",
    "population": "988"
  },
  "Bald Head Island, North Carolina": {
    "state": "37",
    "place": "03150",
    "population": "268"
  },
  "Grandfather Village, North Carolina": {
    "state": "37",
    "place": "27324",
    "population": "95"
  },
  "Cedar Rock, North Carolina": {
    "state": "37",
    "place": "11352",
    "population": "301"
  },
  "Chimney Rock Village, North Carolina": {
    "state": "37",
    "place": "12460",
    "population": "140"
  },
  "Clemmons, North Carolina": {
    "state": "37",
    "place": "12960",
    "population": "21163"
  },
  "Cofield, North Carolina": {
    "state": "37",
    "place": "13460",
    "population": "267"
  },
  "Flat Rock, North Carolina": {
    "state": "37",
    "place": "23600",
    "population": "3486"
  },
  "Forest Hills, North Carolina": {
    "state": "37",
    "place": "24170",
    "population": "303"
  },
  "Foxfire, North Carolina": {
    "state": "37",
    "place": "24570",
    "population": "1288"
  },
  "Lake Park, North Carolina": {
    "state": "37",
    "place": "36512",
    "population": "3269"
  },
  "Marvin, North Carolina": {
    "state": "37",
    "place": "41720",
    "population": "6358"
  },
  "Misenheimer, North Carolina": {
    "state": "37",
    "place": "43580",
    "population": "650"
  },
  "St. Helena, North Carolina": {
    "state": "37",
    "place": "58620",
    "population": "417"
  },
  "Simpson, North Carolina": {
    "state": "37",
    "place": "62040",
    "population": "390"
  },
  "Pinehurst, North Carolina": {
    "state": "37",
    "place": "51940",
    "population": "17581"
  },
  "Sugar Mountain, North Carolina": {
    "state": "37",
    "place": "65530",
    "population": "371"
  },
  "Tobaccoville, North Carolina": {
    "state": "37",
    "place": "67720",
    "population": "2578"
  },
  "Walnut Creek, North Carolina": {
    "state": "37",
    "place": "70820",
    "population": "1084"
  },
  "Wesley Chapel, North Carolina": {
    "state": "37",
    "place": "71940",
    "population": "8681"
  },
  "Whispering Pines, North Carolina": {
    "state": "37",
    "place": "73140",
    "population": "4987"
  }
}
